miintoapi/miintoapi.py
miinto_api_wrapper-1.1.0.dist-info/LICENCE.md
miinto_api_wrapper-1.1.0.dist-info/METADATA
miinto_api_wrapper-1.1.0.dist-info/WHEEL
miinto_api_wrapper-1.1.0.dist-info/top_level.txt
miinto_api_wrapper-1.1.0.dist-info/RECORD
