Metadata-Version: 2.1
Name: miinto-api-wrapper
Version: 1.1.0
Summary: A simple and stupid Miinto API wrapper
Home-page: https://github.com/giuseppechecchia/miinto-api-wrapper
Author: Giuseppe Checchia
Author-email: giuseppechecchia@gmail.com
License: MIT
Platform: UNKNOWN
Classifier: License :: OSI Approved :: MIT License
Classifier: Programming Language :: Python :: 3
Classifier: Programming Language :: Python :: 3.7
Classifier: Operating System :: OS Independent
Requires-Python: >=3.6
Requires-Dist: urlparse2
